awslabs/__init__.py
awslabs/aurora_dsql_mcp_server/__init__.py
awslabs/aurora_dsql_mcp_server/consts.py
awslabs/aurora_dsql_mcp_server/mutable_sql_detector.py
awslabs/aurora_dsql_mcp_server/server.py
awslabs_aurora_dsql_mcp_server-1.0.13.dist-info/METADATA
awslabs_aurora_dsql_mcp_server-1.0.13.dist-info/WHEEL
awslabs_aurora_dsql_mcp_server-1.0.13.dist-info/entry_points.txt
awslabs_aurora_dsql_mcp_server-1.0.13.dist-info/licenses/LICENSE
awslabs_aurora_dsql_mcp_server-1.0.13.dist-info/licenses/NOTICE
awslabs_aurora_dsql_mcp_server-1.0.13.dist-info/RECORD
