Metadata-Version: 2.4
Name: awslabs.aurora-dsql-mcp-server
Version: 1.0.13
Summary: An AWS Labs Model Context Protocol (MCP) server for Aurora DSQL
Project-URL: homepage, https://awslabs.github.io/mcp/
Project-URL: docs, https://awslabs.github.io/mcp/servers/aurora-dsql-mcp-server/
Project-URL: documentation, https://awslabs.github.io/mcp/servers/aurora-dsql-mcp-server/
Project-URL: repository, https://github.com/awslabs/mcp.git
Project-URL: changelog, https://github.com/awslabs/mcp/blob/main/src/aurora-dsql-mcp-server/CHANGELOG.md
Author: Amazon Web Services, Ram Dwivedula, Yoni Shalom
Author-email: AWSLabs MCP <203918161+awslabs-mcp@users.noreply.github.com>
License: Apache-2.0
License-File: LICENSE
License-File: NOTICE
Classifier: License :: OSI Approved :: Apache Software License
Classifier: Operating System :: OS Independent
Classifier: Programming Language :: Python
Classifier: Programming Language :: Python :: 3
Classifier: Programming Language :: Python :: 3.10
Classifier: Programming Language :: Python :: 3.11
Classifier: Programming Language :: Python :: 3.12
Classifier: Programming Language :: Python :: 3.13
Requires-Python: >=3.10
Requires-Dist: boto3>=1.38.5
Requires-Dist: botocore>=1.38.5
Requires-Dist: httpx>=0.27.0
Requires-Dist: loguru>=0.7.0
Requires-Dist: mcp[cli]>=1.23.0
Requires-Dist: psycopg[binary]>=3.0
Requires-Dist: pydantic>=2.10.6
